{
  "contatos": [
    {
      "nome": "Maria Castro",
      "telefone": "(93) 92167-9467",
      "email": "maria@email.com",
      "aniversario": "30/04/2002",
      "redes": "",
      "observacoes": "",
      "id": 1
    },
    {
      "nome": "Diego Haland",
      "telefone": "(82) 93635-9369",
      "email": "diego@email.com",
      "aniversario": "31/05/1997",
      "redes": "haland.di",
      "observacoes": "",
      "id": 2
    },
    {
      "nome": "Thamires Lino",
      "telefone": "(11) 976438900",
      "email": "thamires@email.com",
      "aniversario": "",
      "redes": "",
      "observacoes": "",
      "id": 3
    },
    {
      "nome": "Vitor Oliveira",
      "telefone": "(84) 93771-2646",
      "email": "vitor@uorak.com",
      "aniversario": "10/08/2002",
      "redes": "@vitor.vitor",
      "observacoes": "",
      "id": 4
    },
    {
      "nome": "Henrique Passos",
      "telefone": "(34) 92385-2624",
      "email": "henrique@nry.com",
      "aniversario": "23/11/1994",
      "redes": "passos.henrique",
      "observacoes": "",
      "id": 5
    },
    {
      "nome": "Beatriz Alves",
      "telefone": "(68) 92275-7033",
      "email": "beatriz@vnjp.org",
      "aniversario": "27/03/2001",
      "redes": "beatriz.alves",
      "observacoes": "",
      "id": 6
    }
  ]
}